pydriller/__init__.py
pydriller/git.py
pydriller/repository.py
pydriller/domain/__init__.py
pydriller/domain/commit.py
pydriller/domain/developer.py
pydriller/metrics/__init__.py
pydriller/metrics/process/__init__.py
pydriller/metrics/process/change_set.py
pydriller/metrics/process/code_churn.py
pydriller/metrics/process/commits_count.py
pydriller/metrics/process/contributors_count.py
pydriller/metrics/process/contributors_experience.py
pydriller/metrics/process/history_complexity.py
pydriller/metrics/process/hunks_count.py
pydriller/metrics/process/lines_count.py
pydriller/metrics/process/process_metric.py
pydriller/utils/__init__.py
pydriller/utils/conf.py
PyDriller-2.5.1.dist-info/LICENSE
PyDriller-2.5.1.dist-info/METADATA
PyDriller-2.5.1.dist-info/WHEEL
PyDriller-2.5.1.dist-info/top_level.txt
PyDriller-2.5.1.dist-info/RECORD
