Metadata-Version: 2.1
Name: PyDriller
Version: 2.5.1
Summary: Framework for MSR
Home-page: https://github.com/ishepard/pydriller
Author: Davide Spadini
Author-email: spadini.davide@gmail.com
License: Apache License
Classifier: Development Status :: 5 - Production/Stable
Classifier: Environment :: Console
Classifier: Intended Audience :: Developers
Classifier: Intended Audience :: Science/Research
Classifier: License :: OSI Approved :: Apache Software License
Classifier: Programming Language :: Python :: 3.6
Classifier: Programming Language :: Python :: 3.7
Classifier: Programming Language :: Python :: 3.8
Classifier: Programming Language :: Python :: 3.9
Classifier: Topic :: Software Development :: Libraries :: Python Modules
Classifier: Operating System :: OS Independent
Classifier: Operating System :: POSIX
Classifier: Operating System :: Microsoft :: Windows
Classifier: Operating System :: MacOS :: MacOS X
Requires-Python: >=3.5
License-File: LICENSE
Requires-Dist: gitpython
Requires-Dist: pytz
Requires-Dist: types-pytz
Requires-Dist: lizard
